{
  "production": true,
  "application": {
    "baseUrl":"http://localhost:4200",
    "name": "ABPTestProject",
    "logoUrl": ""
  },
  "oAuthConfig": {
    "issuer": "https://localhost:44354",
    "redirectUri": "http://localhost:4200",
    "clientId": "ABPTestProject_App",
    "responseType": "code",
    "scope": "offline_access openid profile email phone ABPTestProject"
  },
  "apis": {
    "default": {
      "url": "https://localhost:44354",
      "rootNamespace": "ABPTestProject"
    },
    "AbpAccountPublic": {
      "url": "https://localhost:44354",
      "rootNamespace": "AbpAccountPublic"
    }
  }
}